setup.py
/Users/dan/src/oplogutils/scripts/oplog-trim
oplogutils/__init__.py
oplogutils/_core.py
oplogutils/_counter.py
oplogutils/_trimmer.py
oplogutils.egg-info/PKG-INFO
oplogutils.egg-info/SOURCES.txt
oplogutils.egg-info/dependency_links.txt
oplogutils.egg-info/requires.txt
oplogutils.egg-info/top_level.txt
test/test_core.py
test/test_counter.py
test/test_trimmer.py