Metadata-Version: 1.0
Name: oplogutils
Version: 0.1
Summary: A oplog editing utility for mongodb.
Home-page: UNKNOWN
Author: Dan McKinley
Author-email: dan@etsy.com
License: GPL v3
Keywords: mongodb oplog backup restore utility
Platform: UNKNOWN
